this_is.py
this_is-1.0.4.dist-info/METADATA
this_is-1.0.4.dist-info/WHEEL
this_is-1.0.4.dist-info/top_level.txt
this_is-1.0.4.dist-info/RECORD
