Metadata-Version: 2.1
Name: this-is
Version: 1.0.4
Summary: This is Zen of Python by Tim Peters
Home-page: https://github.com/FernandoCelmer/this-is-python
Author: Fernando Celmer
Author-email: email@fernandocelmer.com
Classifier: Programming Language :: Python :: 3
Classifier: License :: OSI Approved :: MIT License
Classifier: Operating System :: OS Independent
Requires-Python: >=3.6
